MANIFEST.in
README.md
setup.cfg
setup.py
django_shard_library.egg-info/PKG-INFO
django_shard_library.egg-info/SOURCES.txt
django_shard_library.egg-info/dependency_links.txt
django_shard_library.egg-info/requires.txt
django_shard_library.egg-info/top_level.txt
requirements/base.txt
requirements/development.txt
shard/__init__.py
shard/admin.py
shard/apps.py
shard/constants.py
shard/exceptions.py
shard/fields.py
shard/managers.py
shard/mixins.py
shard/models.py
shard/providers.py
shard/queryset.py
shard/config/__init__.py
shard/config/database_config.py
shard/config/helper.py
shard/management/__init__.py
shard/management/commands/__init__.py
shard/management/commands/execute_query_command.py
shard/management/commands/execute_query_on_all_shard_command.py
shard/management/commands/get_shard_command.py
shard/routers/__init__.py
shard/routers/base.py
shard/routers/shard.py
shard/routers/specific.py
shard/services/__init__.py
shard/services/execute_query_service.py
shard/services/query_file_handler.py
shard/strategy/__init__.py
shard/strategy/id_generation/__init__.py
shard/strategy/id_generation/base.py
shard/strategy/id_generation/nanosecond.py
shard/strategy/id_generation/table.py
shard/strategy/id_generation/uuid.py
shard/strategy/routing/__init__.py
shard/strategy/routing/base.py
shard/strategy/routing/random.py
shard/utils/__init__.py
shard/utils/database.py
shard/utils/execute.py
shard/utils/memorize.py
shard/utils/replica.py
shard/utils/shard.py
shard/utils/shard_key.py
shard/utils/consistent_hash/__init__.py
shard/utils/consistent_hash/con_hash.py
shard/utils/consistent_hash/node.py
shard/utils/consistent_hash/pool.py
shard_static/__init__.py
shard_static/exceptions.py
shard_static/managers.py
shard_static/mixins.py
shard_static/models.py
shard_static/routers.py
shard_static/transmitter.py
tests/migrations/0001_initial.py
tests/migrations/0002_statictransmitstatus.py
tests/migrations/0003_shardstatictransmittableb.py
tests/migrations/__init__.py