Metadata-Version: 1.1
Name: django-shard-library
Version: 0.1.0
Summary: Django Shard Library
Home-page: https://github.com/ridi/django-shard-library
Author: UNKNOWN
Author-email: UNKNOWN
License: BSD
Keywords: django,shard,ridi,ridibooks
Platform: UNKNOWN
Classifier: Development Status :: 3 - Alpha
Classifier: Intended Audience :: Developers
Classifier: License :: OSI Approved :: BSD License
Classifier: Framework :: Django :: 2.0
Classifier: Programming Language :: Python :: 3.6
